fifomemory.v
module fifomemory#(parameter WIDTH =8, DEPTH =8, PTRWIDTH = $clog2(DEPTH) )(
        output reg [WIDTH-1:0] data_out,
        input empty, full,
        
        input  w_en,
        input  r_en,
        input [WIDTH-1:0] data_in,
        input wclk,
        input rclk,
        input [PTRWIDTH:0] b_wptr,
        input [PTRWIDTH:0] b_rptr
        


);

    reg [WIDTH-1:0] fifo [0:DEPTH-1];

    always@(posedge wclk) begin
        if(w_en & !full) begin
            fifo[b_wptr]<=data_in;
        end
    end

    always@(posedge rclk) begin
        if(r_en &!empty) begin
            data_out<=fifo[b_rptr];
        end
    end

endmodule

g2bconverter2.v
module g2bconverter2 #(parameter width =4) (output wire [width-1:0]data_out, input wire [width-1:0] data_in);

    genvar i;
    assign data_out[width-1] = data_in[width-1];
    generate for(i=width-2;i>=0;i=i-1) begin
        assign data_out[i] = data_out[i+1] ^ data_in[i];
        end
    endgenerate

endmodule

readpointerhandler.v
//`include "g2bconverter2.v"
module readpointerhandler #(parameter PTRWIDTH =3)(output reg [PTRWIDTH:0] b_rptr, 
                                                    output reg [PTRWIDTH:0] g_rptr,
                                                    output reg empty,
                                                    input [PTRWIDTH:0] g_wptr_sync,
                                                    input rrst_n,
                                                    input rclk,
                                                    input r_en);

wire [PTRWIDTH:0] b_rptr_next ;

assign b_rptr_next = b_rptr + (r_en & !empty); // Try taking read reset into consideration for this while doing waveform analysis
wire [PTRWIDTH:0]binary;

always @(posedge rclk or negedge rrst_n) begin
    if(rrst_n==0) begin
        b_rptr<=0;
        g_rptr<=0;
        //empty<=0;

    end
    else begin
        if(!empty & r_en) begin
        b_rptr<= b_rptr_next;
        g_rptr<= (b_rptr_next) ^ b_rptr_next>>1;
        end
    end
end

g2bconverter2  #(.width(PTRWIDTH+1))uut (binary,g_wptr_sync);


// always @(posedge rclk or negedge rrst_n) begin
//     if(rrst_n==0) empty<=0;
//     else empty <= (b_rptr == binary);
// end

always @(posedge rclk or negedge rrst_n) begin
    //if(rrst_n==0) assign empty =0;
      empty <= (b_rptr==binary);
end


endmodule

writepointerhandler.v
`include "g2bconverter2.v"
module writepointerhandler #(parameter PTRWIDTH =3)(output reg [PTRWIDTH:0] b_wptr, 
                           output reg [PTRWIDTH:0] g_wptr,
                           output reg full,
                           input [PTRWIDTH:0] g_rptr_sync,
                           input wrst_n, 
                           input wclk, 
                           input w_en);


    //wire [PTRWIDTH:0] gray;
    wire [PTRWIDTH:0] binary;
    //g2bconverter2 #(.width(PTRWIDTH+1)) uut(gray,b_wptr);
    // Making a an assignment ot parallely store next stage. If I do it in the alwyas block the grey code conversion takes places at the next clock cycle hence there my be a loss of synchronisation
   wire [PTRWIDTH:0] b_wptr_next;
   assign b_wptr_next = b_wptr+(w_en & !full);
    
    always@(posedge wclk or negedge wrst_n) begin
        if(wrst_n==0) begin
            b_wptr<=0;
            g_wptr<=0;
            full<=0;
        end
        else begin
            if(!full && w_en) begin
                b_wptr <= b_wptr_next;
                g_wptr <= b_wptr_next ^ (b_wptr_next>>1);
            end
        end
    end

    
    //g2bconverter2 uut(gray,b_wptr);
    g2bconverter2  #(.width(PTRWIDTH+1))uut2 (binary,g_rptr_sync);

   //always @(posedge wclk) 
    //assign full = b_wptr[PTRWIDTH]!=binary[PTRWIDTH] & b_wptr[PTRWIDTH-1:0] == binary [PTRWIDTH-1:0];
    //assign empty = b_wptr == binary;
    

    always @(posedge wclk or negedge wrst_n) begin
        //if(wrst_n==0) full<=0;
        full <= b_wptr[PTRWIDTH]!=binary[PTRWIDTH] & b_wptr[PTRWIDTH-1:0] == binary [PTRWIDTH-1:0];

    end

endmodule

two_fsynchroniser.v
module two_fsynchroniser #(parameter WIDTH =3) (output reg [WIDTH:0]sync_out, input [WIDTH:0] data_in, input clk, input reset_n);
    reg [WIDTH:0]q1;
always @(posedge clk) begin// Sycnhronous Reset
    if(reset_n==0) begin
        q1<=0;
        sync_out<=0;
        end
    else begin 
        q1<=data_in;
        sync_out<=q1;
    end
end
endmodule

asynchronous_fifo.v
`include "fifomemory.v"
`include "readpointerhandler.v"
`include "writepointerhandler.v"
`include "two_fsynchroniser.v"
//`include "g2bconverter2.v"

module asynchronous_fifo #(parameter DEPTH=8, DATA_WIDTH = 8)(
    output [DATA_WIDTH-1:0] data_out,
    output full, empty,
    input [DATA_WIDTH-1:0] data_in,
    input wclk, wrst_n,
    input rclk, rrst_n,
    input w_en, r_en
    
    
    
);

parameter PTR_WIDTH = $clog2(DEPTH);

// Synchronization signals
wire [PTR_WIDTH:0] g_wptr_sync, g_rptr_sync;
wire [PTR_WIDTH:0] b_wptr, b_rptr;
wire [PTR_WIDTH:0] g_wptr, g_rptr;

// Memory address wires
wire [PTR_WIDTH-1:0] waddr, raddr;

// Instantiate synchronizers
two_fsynchroniser #(PTR_WIDTH) sync_wptr (g_wptr_sync, g_wptr, rclk, rrst_n);
two_fsynchroniser #(PTR_WIDTH) sync_rptr (g_rptr_sync, g_rptr, wclk, wrst_n);

// Instantiate write pointer handler
writepointerhandler #(PTR_WIDTH) wptr_h(
    .b_wptr(b_wptr),
    .g_wptr(g_wptr),
    .full(full),
    .wrst_n(wrst_n),
    .wclk(wclk),
    .w_en(w_en),
    .g_rptr_sync(g_rptr_sync)
);

// Instantiate read pointer handler
readpointerhandler #(PTR_WIDTH) rptr_h(
    .b_rptr(b_rptr),
    .g_rptr(g_rptr),
    .g_wptr_sync(g_wptr_sync),
    .rrst_n(rrst_n),
    .empty(empty),
    .rclk(rclk),
    .r_en(r_en)
);

// Instantiate FIFO memory
fifomemory #(DEPTH, DATA_WIDTH) fifom (
    .data_out(data_out),
    .empty(empty),
    .full(full),
    .w_en(w_en),
    .r_en(r_en),
    .data_in(data_in),
    .wclk(wclk),
    .rclk(rclk),
    .b_wptr(b_wptr),
    .b_rptr(b_rptr)
);

endmodule

tb_asyncfifo.v
`include "asynchronous_fifo.v"

module tb_asyncfifo;

  parameter DATA_WIDTH = 8;
  parameter DEPTH = 8;

  // Testbench signals
  reg wclk, wrst_n;
  reg rclk, rrst_n;
  reg w_en, r_en;
  reg [DATA_WIDTH-1:0] data_in;
  wire [DATA_WIDTH-1:0] data_out;
  wire full, empty;

  // Instantiate the asynchronous FIFO
  asynchronous_fifo #(DEPTH, DATA_WIDTH) as_fifo (
    .wclk(wclk),
    .wrst_n(wrst_n),
    .rclk(rclk),
    .rrst_n(rrst_n),
    .w_en(w_en),
    .r_en(r_en),
    .data_in(data_in),
    .data_out(data_out),
    .full(full),
    .empty(empty)
  );

  // Generate write clock
  always #10 wclk = ~wclk;

  // Generate read clock
  always #15 rclk = ~rclk;

  // Task to write data to the FIFO
  task write_data(input [DATA_WIDTH-1:0] data);
    begin
      @(posedge wclk);
      if (!full) begin
        w_en = 1;
        data_in = data;
        @(posedge wclk);
        w_en = 0;
        $display("Time %0t: Wrote data = %h", $time, data);
      end else begin
        $display("Time %0t: FIFO is full. Cannot write data = %h", $time, data);
      end
    end
  endtask

  // Task to read data from the FIFO
  task read_data();
    begin
      @(posedge rclk);
      if (!empty) begin
        r_en = 1;
        @(posedge rclk);
        r_en = 0;
        $display("Time %0t: Read data = %h", $time, data_out);
      end else begin
        $display("Time %0t: FIFO is empty. Cannot read data", $time);
      end
    end
  endtask

  initial begin
    // Initialize signals
    wclk = 0;
    rclk = 0;
    wrst_n = 0;
    rrst_n = 0;
    w_en = 0;
    r_en = 0;
    data_in = 0;

    // Apply reset
    @(posedge wclk);
    wrst_n = 1;
    rrst_n = 1;
    $display("Time %0t: Reset applied", $time);

    // Write data to the FIFO
    write_data(8'hA1);
    write_data(8'hB2);
    write_data(8'hC3);
    write_data(8'hD4);
    write_data(8'hE5);
    write_data(8'hF6);
    write_data(8'h07);
    write_data(8'h18);

    // Attempt to write when full
    write_data(8'hFF);

    // Read data from the FIFO
    read_data();
    read_data();
    read_data();
    read_data();
    read_data();
    read_data();
    read_data();
    read_data();

    // Attempt to read when empty
    read_data();

    // Test reset functionality during operation
    @(posedge wclk);
    wrst_n = 0;
    rrst_n = 0;
    $display("Time %0t: Reset during operation", $time);

    @(posedge wclk);
    wrst_n = 1;
    rrst_n = 1;
    $display("Time %0t: Reset released", $time);

    // Write and read again after reset
    write_data(8'hAA);
    write_data(8'hBB);
    write_data(8'hC3);
    write_data(8'hD4);
    write_data(8'hE5);
    write_data(8'hF6);
    write_data(8'h07);
    write_data(8'h18);

    write_data(8'hFF);
    read_data();
    read_data();
    read_data();
    read_data();
    read_data();
    read_data();
    read_data();
    read_data();
    read_data();


    @(posedge wclk);
    wrst_n = 0;
    rrst_n = 0;
    $display("Time %0t: Reset during operation", $time);

    @(posedge wclk);
    wrst_n = 1;
    rrst_n = 1;
    $display("Time %0t: Reset released", $time);
    //r_en =1;
   
    write_data(8'hAA);
    read_data();
    
    write_data(8'hBB);
    
    read_data();
    #10
    $finish;
  end

  initial begin
    $dumpfile("asyncfifo_tb.vcd");
    $dumpvars(0, tb_asyncfifo);
  end

endmodule

asyncfifo_tb.vcd
$date
	Sun Jul 28 23:05:58 2024
$end
$version
	Icarus Verilog
$end
$timescale
	1s
$end
$scope module tb_asyncfifo $end
$var wire 1 ! full $end
$var wire 1 " empty $end
$var wire 8 # data_out [7:0] $end
$var parameter 32 $ DATA_WIDTH $end
$var parameter 32 % DEPTH $end
$var reg 8 & data_in [7:0] $end
$var reg 1 ' r_en $end
$var reg 1 ( rclk $end
$var reg 1 ) rrst_n $end
$var reg 1 * w_en $end
$var reg 1 + wclk $end
$var reg 1 , wrst_n $end
$scope module as_fifo $end
$var wire 8 - data_in [7:0] $end
$var wire 1 ' r_en $end
$var wire 1 ( rclk $end
$var wire 1 ) rrst_n $end
$var wire 1 * w_en $end
$var wire 1 + wclk $end
$var wire 1 , wrst_n $end
$var wire 4 . g_wptr_sync [3:0] $end
$var wire 4 / g_wptr [3:0] $end
$var wire 4 0 g_rptr_sync [3:0] $end
$var wire 4 1 g_rptr [3:0] $end
$var wire 1 ! full $end
$var wire 1 " empty $end
$var wire 8 2 data_out [7:0] $end
$var wire 4 3 b_wptr [3:0] $end
$var wire 4 4 b_rptr [3:0] $end
$var parameter 32 5 DATA_WIDTH $end
$var parameter 32 6 DEPTH $end
$var parameter 32 7 PTR_WIDTH $end
$scope module fifom $end
$var wire 8 8 data_in [7:0] $end
$var wire 1 ' r_en $end
$var wire 1 ( rclk $end
$var wire 1 * w_en $end
$var wire 1 + wclk $end
$var wire 1 ! full $end
$var wire 1 " empty $end
$var wire 4 9 b_wptr [3:0] $end
$var wire 4 : b_rptr [3:0] $end
$var parameter 32 ; DEPTH $end
$var parameter 32 < PTRWIDTH $end
$var parameter 32 = WIDTH $end
$var reg 8 > data_out [7:0] $end
$upscope $end
$scope module rptr_h $end
$var wire 1 ' r_en $end
$var wire 1 ( rclk $end
$var wire 1 ) rrst_n $end
$var wire 4 ? g_wptr_sync [3:0] $end
$var wire 4 @ binary [3:0] $end
$var wire 4 A b_rptr_next [3:0] $end
$var parameter 32 B PTRWIDTH $end
$var reg 4 C b_rptr [3:0] $end
$var reg 1 " empty $end
$var reg 4 D g_rptr [3:0] $end
$scope module uut $end
$var wire 4 E data_out [3:0] $end
$var wire 4 F data_in [3:0] $end
$var parameter 33 G width $end
$scope begin genblk1[0] $end
$var parameter 2 H i $end
$upscope $end
$scope begin genblk1[1] $end
$var parameter 2 I i $end
$upscope $end
$scope begin genblk1[2] $end
$var parameter 3 J i $end
$upscope $end
$upscope $end
$upscope $end
$scope module sync_rptr $end
$var wire 1 + clk $end
$var wire 4 K data_in [3:0] $end
$var wire 1 , reset_n $end
$var parameter 32 L WIDTH $end
$var reg 4 M q1 [3:0] $end
$var reg 4 N sync_out [3:0] $end
$upscope $end
$scope module sync_wptr $end
$var wire 1 ( clk $end
$var wire 1 ) reset_n $end
$var wire 4 O data_in [3:0] $end
$var parameter 32 P WIDTH $end
$var reg 4 Q q1 [3:0] $end
$var reg 4 R sync_out [3:0] $end
$upscope $end
$scope module wptr_h $end
$var wire 4 S g_rptr_sync [3:0] $end
$var wire 1 * w_en $end
$var wire 1 + wclk $end
$var wire 1 , wrst_n $end
$var wire 4 T binary [3:0] $end
$var wire 4 U b_wptr_next [3:0] $end
$var parameter 32 V PTRWIDTH $end
$var reg 4 W b_wptr [3:0] $end
$var reg 1 ! full $end
$var reg 4 X g_wptr [3:0] $end
$scope module uut2 $end
$var wire 4 Y data_in [3:0] $end
$var wire 4 Z data_out [3:0] $end
$var parameter 33 [ width $end
$scope begin genblk1[0] $end
$var parameter 2 \ i $end
$upscope $end
$scope begin genblk1[1] $end
$var parameter 2 ] i $end
$upscope $end
$scope begin genblk1[2] $end
$var parameter 3 ^ i $end
$upscope $end
$upscope $end
$upscope $end
$upscope $end
$scope task read_data $end
$upscope $end
$scope task write_data $end
$var reg 8 _ data [7:0] $end
$upscope $end
$upscope $end
$enddefinitions $end
$comment Show the parameter values. $end
$dumpall
b10 ^
b1 ]
b0 \
b100 [
b11 V
b11 P
b11 L
b10 J
b1 I
b0 H
b100 G
b11 B
b1000 =
b11 <
b1000 ;
b11 7
b1000 6
b1000 5
b1000 %
b1000 $
$end
#0
$dumpvars
bx _
bx Z
bx Y
b0 X
b0 W
b0 U
bx T
bx S
bx R
bx Q
b0 O
bx N
bx M
b0 K
bx F
bx E
b0 D
b0 C
b0 A
bx @
bx ?
bx >
b0 :
b0 9
b0 8
b0 4
b0 3
bx 2
b0 1
bx 0
b0 /
bx .
b0 -
0,
0+
0*
0)
0(
0'
b0 &
bx #
x"
0!
$end
#10
b0 M
x!
b10100001 _
1)
1,
1+
#15
b0 Q
1(
#20
0+
#30
b0 T
b0 Z
b0 0
b0 N
b0 S
b0 Y
b10110010 _
1+
0(
#40
0+
#45
b0 @
b0 E
b0 .
b0 ?
b0 F
b0 R
1(
#50
0!
b11000011 _
1+
#60
0+
0(
#70
b1 U
b11000011 &
b11000011 -
b11000011 8
1*
1+
#75
1"
1(
#80
0+
#90
b1 /
b1 O
b1 X
b1 3
b1 9
b1 W
b1 U
b11010100 _
0*
1+
0(
#100
0+
#105
b1 Q
1(
#110
b10 U
b11010100 &
b11010100 -
b11010100 8
1*
1+
#120
0+
0(
#130
b11 /
b11 O
b11 X
b10 3
b10 9
b10 W
b10 U
b11100101 _
0*
1+
#135
b1 @
b1 E
b1 .
b1 ?
b1 F
b1 R
b11 Q
1(
#140
0+
#150
b11 U
b11100101 &
b11100101 -
b11100101 8
1*
1+
0(
#160
0+
#165
b10 @
b10 E
b11 .
b11 ?
b11 F
b11 R
0"
1(
#170
b10 /
b10 O
b10 X
b11 3
b11 9
b11 W
b11 U
b11110110 _
0*
1+
#180
0+
0(
#190
b100 U
b11110110 &
b11110110 -
b11110110 8
1*
1+
#195
b10 Q
1(
#200
0+
#210
b110 /
b110 O
b110 X
b100 3
b100 9
b100 W
b100 U
b111 _
0*
1+
0(
#220
0+
#225
b11 @
b11 E
b10 .
b10 ?
b10 F
b10 R
b110 Q
1(
#230
b101 U
b111 &
b111 -
b111 8
1*
1+
#240
0+
0(
#250
b111 /
b111 O
b111 X
b101 3
b101 9
b101 W
b101 U
b11000 _
0*
1+
#255
b100 @
b100 E
b110 .
b110 ?
b110 F
b110 R
b111 Q
1(
#260
0+
#270
b110 U
b11000 &
b11000 -
b11000 8
1*
1+
0(
#280
0+
#285
b101 @
b101 E
b111 .
b111 ?
b111 F
b111 R
1(
#290
b101 /
b101 O
b101 X
b110 3
b110 9
b110 W
b110 U
b11111111 _
0*
1+
#300
0+
0(
#310
b111 U
b11111111 &
b11111111 -
b11111111 8
1*
1+
#315
b101 Q
1(
#320
0+
#330
b100 /
b100 O
b100 X
b111 3
b111 9
b111 W
b111 U
0*
1+
0(
#340
0+
#345
b110 @
b110 E
b11000011 #
b11000011 2
b11000011 >
b101 .
b101 ?
b101 F
b101 R
b100 Q
b1 A
1'
1(
#350
1+
#360
0+
0(
#370
1+
#375
b111 @
b111 E
b100 .
b100 ?
b100 F
b100 R
b1 1
b1 D
b1 K
b1 4
b1 :
b1 C
b1 A
0'
1(
#380
0+
#390
b1 M
1+
0(
#400
0+
#405
b11010100 #
b11010100 2
b11010100 >
b10 A
1'
1(
#410
b1 T
b1 Z
b1 0
b1 N
b1 S
b1 Y
1+
#420
0+
0(
#430
1+
#435
b11 1
b11 D
b11 K
b10 4
b10 :
b10 C
b10 A
0'
1(
#440
0+
#450
b11 M
1+
0(
#460
0+
#465
b11100101 #
b11100101 2
b11100101 >
b11 A
1'
1(
#470
b10 T
b10 Z
b11 0
b11 N
b11 S
b11 Y
1+
#480
0+
0(
#490
1+
#495
b10 1
b10 D
b10 K
b11 4
b11 :
b11 C
b11 A
0'
1(
#500
0+
#510
b10 M
1+
0(
#520
0+
#525
b11110110 #
b11110110 2
b11110110 >
b100 A
1'
1(
#530
b11 T
b11 Z
b10 0
b10 N
b10 S
b10 Y
1+
#540
0+
0(
#550
1+
#555
b110 1
b110 D
b110 K
b100 4
b100 :
b100 C
b100 A
0'
1(
#560
0+
#570
b110 M
1+
0(
#580
0+
#585
b111 #
b111 2
b111 >
b101 A
1'
1(
#590
b100 T
b100 Z
b110 0
b110 N
b110 S
b110 Y
1+
#600
0+
0(
#610
1+
#615
b111 1
b111 D
b111 K
b101 4
b101 :
b101 C
b101 A
0'
1(
#620
0+
#630
b111 M
1+
0(
#640
0+
#645
b11000 #
b11000 2
b11000 >
b110 A
1'
1(
#650
b101 T
b101 Z
b111 0
b111 N
b111 S
b111 Y
1+
#660
0+
0(
#670
1+
#675
b101 1
b101 D
b101 K
b110 4
b110 :
b110 C
b110 A
0'
1(
#680
0+
#690
b101 M
1+
0(
#700
0+
#705
b11111111 #
b11111111 2
b11111111 >
b111 A
1'
1(
#710
b110 T
b110 Z
b101 0
b101 N
b101 S
b101 Y
1+
#720
0+
0(
#730
1+
#735
b100 1
b100 D
b100 K
b111 4
b111 :
b111 C
b111 A
0'
1(
#740
0+
#750
b100 M
1+
0(
#760
0+
#765
bx #
bx 2
bx >
1"
b111 A
1'
1(
#770
b111 T
b111 Z
b100 0
b100 N
b100 S
b100 Y
1+
#780
0+
0(
#790
1+
#795
0'
1(
#800
0+
#810
1+
0(
#820
0+
#825
1(
#830
b0 T
b0 Z
b0 1
b0 D
b0 K
b0 A
b0 4
b0 :
b0 C
b0 /
b0 O
b0 X
b0 U
b0 3
b0 9
b0 W
b0 0
b0 N
b0 S
b0 Y
b0 M
0)
0,
1+
#840
0+
0(
#850
b10101010 _
1)
1,
1+
#855
b0 Q
0"
1(
#860
0+
#870
b1 U
b10101010 &
b10101010 -
b10101010 8
1*
1+
0(
#880
0+
#885
b0 @
b0 E
b0 .
b0 ?
b0 F
b0 R
1(
#890
b1 /
b1 O
b1 X
b1 3
b1 9
b1 W
b1 U
b10111011 _
0*
1+
#900
0+
0(
#910
b10 U
b10111011 &
b10111011 -
b10111011 8
1*
1+
#915
b1 Q
1"
1(
#920
0+
#930
b11 /
b11 O
b11 X
b10 3
b10 9
b10 W
b10 U
b11000011 _
0*
1+
0(
#940
0+
#945
b1 @
b1 E
b1 .
b1 ?
b1 F
b1 R
b11 Q
1(
#950
b11 U
b11000011 &
b11000011 -
b11000011 8
1*
1+
#960
0+
0(
#970
b10 /
b10 O
b10 X
b11 3
b11 9
b11 W
b11 U
b11010100 _
0*
1+
#975
b10 @
b10 E
b11 .
b11 ?
b11 F
b11 R
b10 Q
0"
1(
#980
0+
#990
b100 U
b11010100 &
b11010100 -
b11010100 8
1*
1+
0(
#1000
0+
#1005
b11 @
b11 E
b10 .
b10 ?
b10 F
b10 R
1(
#1010
b110 /
b110 O
b110 X
b100 3
b100 9
b100 W
b100 U
b11100101 _
0*
1+
#1020
0+
0(
#1030
b101 U
b11100101 &
b11100101 -
b11100101 8
1*
1+
#1035
b110 Q
1(
#1040
0+
#1050
b111 /
b111 O
b111 X
b101 3
b101 9
b101 W
b101 U
b11110110 _
0*
1+
0(
#1060
0+
#1065
b100 @
b100 E
b110 .
b110 ?
b110 F
b110 R
b111 Q
1(
#1070
b110 U
b11110110 &
b11110110 -
b11110110 8
1*
1+
#1080
0+
0(
#1090
b101 /
b101 O
b101 X
b110 3
b110 9
b110 W
b110 U
b111 _
0*
1+
#1095
b101 @
b101 E
b111 .
b111 ?
b111 F
b111 R
b101 Q
1(
#1100
0+
#1110
b111 U
b111 &
b111 -
b111 8
1*
1+
0(
#1120
0+
#1125
b110 @
b110 E
b101 .
b101 ?
b101 F
b101 R
1(
#1130
b100 /
b100 O
b100 X
b111 3
b111 9
b111 W
b111 U
b11000 _
0*
1+
#1140
0+
0(
#1150
b1000 U
b11000 &
b11000 -
b11000 8
1*
1+
#1155
b100 Q
1(
#1160
0+
#1170
b1100 /
b1100 O
b1100 X
b1000 3
b1000 9
b1000 W
b1000 U
b11111111 _
0*
1+
0(
#1180
0+
#1185
b111 @
b111 E
b100 .
b100 ?
b100 F
b100 R
b1100 Q
1(
#1190
1!
b1000 U
b11111111 &
b11111111 -
b11111111 8
1*
1+
#1200
0+
0(
#1210
0*
1+
#1215
b1000 @
b1000 E
b1100 .
b1100 ?
b1100 F
b1100 R
b10101010 #
b10101010 2
b10101010 >
b1 A
1'
1(
#1220
0+
#1230
1+
0(
#1240
0+
#1245
b1 1
b1 D
b1 K
b1 4
b1 :
b1 C
b1 A
0'
1(
#1250
b1 M
1+
#1260
0+
0(
#1270
b1 T
b1 Z
b1 0
b1 N
b1 S
b1 Y
1+
#1275
b10111011 #
b10111011 2
b10111011 >
b10 A
1'
1(
#1280
0+
#1290
0!
1+
0(
#1300
0+
#1305
b11 1
b11 D
b11 K
b10 4
b10 :
b10 C
b10 A
0'
1(
#1310
b11 M
1+
#1320
0+
0(
#1330
b10 T
b10 Z
b11 0
b11 N
b11 S
b11 Y
1+
#1335
b11000011 #
b11000011 2
b11000011 >
b11 A
1'
1(
#1340
0+
#1350
1+
0(
#1360
0+
#1365
b10 1
b10 D
b10 K
b11 4
b11 :
b11 C
b11 A
0'
1(
#1370
b10 M
1+
#1380
0+
0(
#1390
b11 T
b11 Z
b10 0
b10 N
b10 S
b10 Y
1+
#1395
b11010100 #
b11010100 2
b11010100 >
b100 A
1'
1(
#1400
0+
#1410
1+
0(
#1420
0+
#1425
b110 1
b110 D
b110 K
b100 4
b100 :
b100 C
b100 A
0'
1(
#1430
b110 M
1+
#1440
0+
0(
#1450
b100 T
b100 Z
b110 0
b110 N
b110 S
b110 Y
1+
#1455
b11100101 #
b11100101 2
b11100101 >
b101 A
1'
1(
#1460
0+
#1470
1+
0(
#1480
0+
#1485
b111 1
b111 D
b111 K
b101 4
b101 :
b101 C
b101 A
0'
1(
#1490
b111 M
1+
#1500
0+
0(
#1510
b101 T
b101 Z
b111 0
b111 N
b111 S
b111 Y
1+
#1515
b11110110 #
b11110110 2
b11110110 >
b110 A
1'
1(
#1520
0+
#1530
1+
0(
#1540
0+
#1545
b101 1
b101 D
b101 K
b110 4
b110 :
b110 C
b110 A
0'
1(
#1550
b101 M
1+
#1560
0+
0(
#1570
b110 T
b110 Z
b101 0
b101 N
b101 S
b101 Y
1+
#1575
b111 #
b111 2
b111 >
b111 A
1'
1(
#1580
0+
#1590
1+
0(
#1600
0+
#1605
b100 1
b100 D
b100 K
b111 4
b111 :
b111 C
b111 A
0'
1(
#1610
b100 M
1+
#1620
0+
0(
#1630
b111 T
b111 Z
b100 0
b100 N
b100 S
b100 Y
1+
#1635
b11000 #
b11000 2
b11000 >
b1000 A
1'
1(
#1640
0+
#1650
1+
0(
#1660
0+
#1665
b1100 1
b1100 D
b1100 K
b1000 4
b1000 :
b1000 C
b1000 A
0'
1(
#1670
b1100 M
1+
#1680
0+
0(
#1690
b1000 T
b1000 Z
b1100 0
b1100 N
b1100 S
b1100 Y
1+
#1695
bx #
bx 2
bx >
1"
b1000 A
1'
1(
#1700
0+
#1710
1+
0(
#1720
0+
#1725
0'
1(
#1730
b0 T
b0 Z
b0 1
b0 D
b0 K
b0 A
b0 4
b0 :
b0 C
b0 /
b0 O
b0 X
b0 U
b0 3
b0 9
b0 W
b0 0
b0 N
b0 S
b0 Y
b0 M
0)
0,
1+
#1740
0+
0(
#1750
b10101010 _
1)
1,
1+
#1755
b0 Q
0"
1(
#1760
0+
#1770
b1 U
b10101010 &
b10101010 -
b10101010 8
1*
1+
0(
#1780
0+
#1785
b0 @
b0 E
b0 .
b0 ?
b0 F
b0 R
1(
#1790
b1 /
b1 O
b1 X
b1 3
b1 9
b1 W
b1 U
0*
1+
#1800
0+
0(
#1810
1+
#1815
b1 Q
b10101010 #
b10101010 2
b10101010 >
1"
b0 A
1'
1(
#1820
0+
#1830
1+
0(
#1840
0+
#1845
b1 @
b1 E
b1 .
b1 ?
b1 F
b1 R
b10111011 _
0'
1(
#1850
b10 U
b10111011 &
b10111011 -
b10111011 8
1*
1+
#1860
0+
0(
#1870
b11 /
b11 O
b11 X
b10 3
b10 9
b10 W
b10 U
0*
1+
#1875
b11 Q
0"
1(
