g2bconverter2.v
module g2bconverter2 #(parameter width =4) (output wire [width-1:0]data_out, input wire [width-1:0] data_in);

    genvar i;
    assign data_out[width-1] = data_in[width-1];
    generate for(i=width-2;i>=0;i=i-1) begin
        assign data_out[i] = data_out[i+1] ^ data_in[i];
        end
    endgenerate

endmodule

tb_g2bconverter.v
`include "g2bconverter2.v"
module tb_g2bconverter;

    parameter WIDTH = 4;
    reg [WIDTH-1:0] gray;
    wire [WIDTH-1:0] binary;

    // Instantiate the gray to binary converter
    g2bconverter2 #(.width(WIDTH)) converter (
        .data_out(binary),
        .data_in(gray)
    );

    initial begin
        // Apply Gray code test vectors and display results
        gray = 'b000; #10;
        $display("Gray: %b, Binary: %b", gray, binary);
        
        gray = 3'b001; #10;
        $display("Gray: %b, Binary: %b", gray, binary);
        
        gray = 4'b1100; #10;
        $display("Gray: %b, Binary: %b", gray, binary);

        gray = 3'b011; #10;
        $display("Gray: %b, Binary: %b", gray, binary);
        
        gray = 3'b010; #10;
        $display("Gray: %b, Binary: %b", gray, binary);
        
        gray = 3'b110; #10;
        $display("Gray: %b, Binary: %b", gray, binary);
        
        gray = 3'b111; #10;
        $display("Gray: %b, Binary: %b", gray, binary);
        
        gray = 3'b101; #10;
        $display("Gray: %b, Binary: %b", gray, binary);
        
        gray = 3'b100; #10;
        $display("Gray: %b, Binary: %b", gray, binary);
        
        $finish;
    end

    initial begin 
        $dumpfile("tb_g2bconverter.vcd");
        $dumpvars(0, tb_g2bconverter);
    end
endmodule

tb_g2bconverter.vcd
$date
	Sun Jul 14 15:37:55 2024
$end
$version
	Icarus Verilog
$end
$timescale
	1s
$end
$scope module tb_g2bconverter $end
$var wire 4 ! binary [3:0] $end
$var parameter 32 " WIDTH $end
$var reg 4 # gray [3:0] $end
$scope module converter $end
$var wire 4 $ data_in [3:0] $end
$var wire 4 % data_out [3:0] $end
$var parameter 32 & width $end
$scope begin genblk1[0] $end
$var parameter 2 ' i $end
$upscope $end
$scope begin genblk1[1] $end
$var parameter 2 ( i $end
$upscope $end
$scope begin genblk1[2] $end
$var parameter 3 ) i $end
$upscope $end
$upscope $end
$upscope $end
$enddefinitions $end
$comment Show the parameter values. $end
$dumpall
b10 )
b1 (
b0 '
b100 &
b100 "
$end
#0
$dumpvars
b0 %
b0 $
b0 #
b0 !
$end
#10
b1 !
b1 %
b1 #
b1 $
#20
b1000 !
b1000 %
b1100 #
b1100 $
#30
b10 !
b10 %
b11 #
b11 $
#40
b11 !
b11 %
b10 #
b10 $
#50
b100 !
b100 %
b110 #
b110 $
#60
b101 !
b101 %
b111 #
b111 $
#70
b110 !
b110 %
b101 #
b101 $
#80
b111 !
b111 %
b100 #
b100 $
